{
  "last_updated": "2026-04-11T00:01:09.109670Z",
  "tournament_day": 8,
  "total_bots": 7,
  "bots": [
    {
      "id": "momentum",
      "status": "ACTIVE",
      "equity": 100.0,
      "pnl": 0.0,
      "trades": 0,
      "win_rate": 0.0,
      "max_drawdown": 0.0,
      "current_drawdown": 0.0,
      "last_heartbeat": "2026-04-11T00:01:01.718336Z",
      "rank": 1
    },
    {
      "id": "mean_reversion",
      "status": "ACTIVE",
      "equity": 100.0,
      "pnl": 0.0,
      "trades": 0,
      "win_rate": 0.0,
      "max_drawdown": 0.0,
      "current_drawdown": 0.0,
      "last_heartbeat": "2026-04-11T00:01:02.865002Z",
      "rank": 2
    },
    {
      "id": "grid",
      "status": "ACTIVE",
      "equity": 100.0,
      "pnl": 0.0,
      "trades": 0,
      "win_rate": 0.0,
      "max_drawdown": 0.0,
      "current_drawdown": 0.0,
      "last_heartbeat": "2026-04-11T00:01:06.066519Z",
      "rank": 3
    },
    {
      "id": "scalping",
      "status": "ACTIVE",
      "equity": 100.0,
      "pnl": 0.0,
      "trades": 0,
      "win_rate": 0.0,
      "max_drawdown": 0.0,
      "current_drawdown": 0.0,
      "last_heartbeat": "2026-04-11T00:01:07.080508Z",
      "rank": 4
    },
    {
      "id": "swing",
      "status": "ACTIVE",
      "equity": 100.0,
      "pnl": 0.0,
      "trades": 0,
      "win_rate": 0.0,
      "max_drawdown": 0.0,
      "current_drawdown": 0.0,
      "last_heartbeat": "2026-04-10T23:56:07.314364Z",
      "rank": 5
    },
    {
      "id": "vwap_reversion",
      "status": "ACTIVE",
      "equity": 100.0,
      "pnl": 0.0,
      "trades": 0,
      "win_rate": 0.0,
      "max_drawdown": 0.0,
      "current_drawdown": 0.0,
      "last_heartbeat": "2026-04-11T00:01:04.023326Z",
      "rank": 6
    },
    {
      "id": "vwap_momentum",
      "status": "ACTIVE",
      "equity": 100.0,
      "pnl": 0.0,
      "trades": 0,
      "win_rate": 0.0,
      "max_drawdown": 0.0,
      "current_drawdown": 0.0,
      "last_heartbeat": "2026-04-11T00:01:05.047594Z",
      "rank": 7
    }
  ],
  "leaderboard": [
    {
      "id": "momentum",
      "status": "ACTIVE",
      "equity": 100.0,
      "pnl": 0.0,
      "trades": 0,
      "win_rate": 0.0,
      "max_drawdown": 0.0,
      "current_drawdown": 0.0,
      "last_heartbeat": "2026-04-11T00:01:01.718336Z",
      "rank": 1
    },
    {
      "id": "mean_reversion",
      "status": "ACTIVE",
      "equity": 100.0,
      "pnl": 0.0,
      "trades": 0,
      "win_rate": 0.0,
      "max_drawdown": 0.0,
      "current_drawdown": 0.0,
      "last_heartbeat": "2026-04-11T00:01:02.865002Z",
      "rank": 2
    },
    {
      "id": "grid",
      "status": "ACTIVE",
      "equity": 100.0,
      "pnl": 0.0,
      "trades": 0,
      "win_rate": 0.0,
      "max_drawdown": 0.0,
      "current_drawdown": 0.0,
      "last_heartbeat": "2026-04-11T00:01:06.066519Z",
      "rank": 3
    },
    {
      "id": "scalping",
      "status": "ACTIVE",
      "equity": 100.0,
      "pnl": 0.0,
      "trades": 0,
      "win_rate": 0.0,
      "max_drawdown": 0.0,
      "current_drawdown": 0.0,
      "last_heartbeat": "2026-04-11T00:01:07.080508Z",
      "rank": 4
    },
    {
      "id": "swing",
      "status": "ACTIVE",
      "equity": 100.0,
      "pnl": 0.0,
      "trades": 0,
      "win_rate": 0.0,
      "max_drawdown": 0.0,
      "current_drawdown": 0.0,
      "last_heartbeat": "2026-04-10T23:56:07.314364Z",
      "rank": 5
    },
    {
      "id": "vwap_reversion",
      "status": "ACTIVE",
      "equity": 100.0,
      "pnl": 0.0,
      "trades": 0,
      "win_rate": 0.0,
      "max_drawdown": 0.0,
      "current_drawdown": 0.0,
      "last_heartbeat": "2026-04-11T00:01:04.023326Z",
      "rank": 6
    },
    {
      "id": "vwap_momentum",
      "status": "ACTIVE",
      "equity": 100.0,
      "pnl": 0.0,
      "trades": 0,
      "win_rate": 0.0,
      "max_drawdown": 0.0,
      "current_drawdown": 0.0,
      "last_heartbeat": "2026-04-11T00:01:05.047594Z",
      "rank": 7
    }
  ],
  "summary": {
    "total_equity": 700.0,
    "total_pnl": 0.0,
    "total_trades": 0,
    "active_bots": 7,
    "suspended_bots": 0,
    "terminated_bots": 0
  }
}