{
  "last_updated": "2026-04-08T21:28:25.588937Z",
  "tournament_day": 5,
  "total_bots": 7,
  "bots": [
    {
      "id": "momentum",
      "status": "ACTIVE",
      "equity": 100.0,
      "pnl": 0.0,
      "trades": 0,
      "win_rate": 0.0,
      "max_drawdown": 0.0,
      "current_drawdown": 0.0,
      "last_heartbeat": "2026-04-08T21:28:18.074572Z",
      "rank": 1
    },
    {
      "id": "mean_reversion",
      "status": "ACTIVE",
      "equity": 100.0,
      "pnl": 0.0,
      "trades": 0,
      "win_rate": 0.0,
      "max_drawdown": 0.0,
      "current_drawdown": 0.0,
      "last_heartbeat": "2026-04-08T21:28:19.143338Z",
      "rank": 2
    },
    {
      "id": "grid",
      "status": "ACTIVE",
      "equity": 100.0,
      "pnl": 0.0,
      "trades": 0,
      "win_rate": 0.0,
      "max_drawdown": 0.0,
      "current_drawdown": 0.0,
      "last_heartbeat": "2026-04-08T21:28:22.514701Z",
      "rank": 3
    },
    {
      "id": "scalping",
      "status": "ACTIVE",
      "equity": 100.0,
      "pnl": 0.0,
      "trades": 0,
      "win_rate": 0.0,
      "max_drawdown": 0.0,
      "current_drawdown": 0.0,
      "last_heartbeat": "2026-04-08T21:28:23.591689Z",
      "rank": 4
    },
    {
      "id": "swing",
      "status": "ACTIVE",
      "equity": 100.0,
      "pnl": 0.0,
      "trades": 0,
      "win_rate": 0.0,
      "max_drawdown": 0.0,
      "current_drawdown": 0.0,
      "last_heartbeat": "2026-04-08T21:25:10.652851Z",
      "rank": 5
    },
    {
      "id": "vwap_reversion",
      "status": "ACTIVE",
      "equity": 100.0,
      "pnl": 0.0,
      "trades": 0,
      "win_rate": 0.0,
      "max_drawdown": 0.0,
      "current_drawdown": 0.0,
      "last_heartbeat": "2026-04-08T21:28:20.317231Z",
      "rank": 6
    },
    {
      "id": "vwap_momentum",
      "status": "ACTIVE",
      "equity": 100.0,
      "pnl": 0.0,
      "trades": 0,
      "win_rate": 0.0,
      "max_drawdown": 0.0,
      "current_drawdown": 0.0,
      "last_heartbeat": "2026-04-08T21:28:21.477573Z",
      "rank": 7
    }
  ],
  "leaderboard": [
    {
      "id": "momentum",
      "status": "ACTIVE",
      "equity": 100.0,
      "pnl": 0.0,
      "trades": 0,
      "win_rate": 0.0,
      "max_drawdown": 0.0,
      "current_drawdown": 0.0,
      "last_heartbeat": "2026-04-08T21:28:18.074572Z",
      "rank": 1
    },
    {
      "id": "mean_reversion",
      "status": "ACTIVE",
      "equity": 100.0,
      "pnl": 0.0,
      "trades": 0,
      "win_rate": 0.0,
      "max_drawdown": 0.0,
      "current_drawdown": 0.0,
      "last_heartbeat": "2026-04-08T21:28:19.143338Z",
      "rank": 2
    },
    {
      "id": "grid",
      "status": "ACTIVE",
      "equity": 100.0,
      "pnl": 0.0,
      "trades": 0,
      "win_rate": 0.0,
      "max_drawdown": 0.0,
      "current_drawdown": 0.0,
      "last_heartbeat": "2026-04-08T21:28:22.514701Z",
      "rank": 3
    },
    {
      "id": "scalping",
      "status": "ACTIVE",
      "equity": 100.0,
      "pnl": 0.0,
      "trades": 0,
      "win_rate": 0.0,
      "max_drawdown": 0.0,
      "current_drawdown": 0.0,
      "last_heartbeat": "2026-04-08T21:28:23.591689Z",
      "rank": 4
    },
    {
      "id": "swing",
      "status": "ACTIVE",
      "equity": 100.0,
      "pnl": 0.0,
      "trades": 0,
      "win_rate": 0.0,
      "max_drawdown": 0.0,
      "current_drawdown": 0.0,
      "last_heartbeat": "2026-04-08T21:25:10.652851Z",
      "rank": 5
    },
    {
      "id": "vwap_reversion",
      "status": "ACTIVE",
      "equity": 100.0,
      "pnl": 0.0,
      "trades": 0,
      "win_rate": 0.0,
      "max_drawdown": 0.0,
      "current_drawdown": 0.0,
      "last_heartbeat": "2026-04-08T21:28:20.317231Z",
      "rank": 6
    },
    {
      "id": "vwap_momentum",
      "status": "ACTIVE",
      "equity": 100.0,
      "pnl": 0.0,
      "trades": 0,
      "win_rate": 0.0,
      "max_drawdown": 0.0,
      "current_drawdown": 0.0,
      "last_heartbeat": "2026-04-08T21:28:21.477573Z",
      "rank": 7
    }
  ],
  "summary": {
    "total_equity": 700.0,
    "total_pnl": 0.0,
    "total_trades": 0,
    "active_bots": 7,
    "suspended_bots": 0,
    "terminated_bots": 0
  }
}